{
  "id": "minimum-cost-to-hire-k-workers",
  "title": "Minimum Cost to Hire K Workers",
  "category": "arrays",
  "difficulty": "Hard",
  "tags": [
    "Arrays",
    "Number Theory"
  ],
  "description": "Find minimum cost to hire k workers given wage and quality constraints",
  "constraints": [
    "See problem statement"
  ],
  "examples": [
    {
      "input": "n=4, wages=[70,50,30,80], qualities=[10,20,5,15], k=2",
      "output": "105.0",
      "explanation": "Step 1: Generate all C(4,2)=6 combinations: (0,1), (0,2), (0,3), (1,2), (1,3), (2,3). Step 2: For each combination: (0,1): ratios=70/10=7.0, 50/20=2.5, max=7.0, sum_qualities=10+20=30, cost=7.0×30=210.0. (0,2): ratios=7.0, 30/5=6.0, max=7.0, sum_qualities=10+5=15, cost=7.0×15=105.0. (0,3): ratios=7.0, 80/15≈5.33, max=7.0, sum_qualities=10+15=25, cost=7.0×25=175.0. (1,2): ratios=2.5, 6.0, max=6.0, sum_qualities=20+5=25, cost=6.0×25=150.0. (1,3): ratios=2.5, 5.33, max=5.33, sum_qualities=20+15=35, cost=5.33×35≈186.67. (2,3): ratios=6.0, 5.33, max=6.0, sum_qualities=5+15=20, cost=6.0×20=120.0. Step 3: Minimum cost = min(210.0, 105.0, 175.0, 150.0, 186.67, 120.0) = 105.0."
    },
    {
      "input": "n=3, wages=[10,20,30], qualities=[1,2,3], k=2",
      "output": "30.0",
      "explanation": "Step 1: Generate all C(3,2)=3 combinations: (0,1), (0,2), (1,2). Step 2: For each combination: (0,1): ratios=10/1=10.0, 20/2=10.0, max=10.0, sum_qualities=1+2=3, cost=10.0×3=30.0. (0,2): ratios=10.0, 30/3=10.0, max=10.0, sum_qualities=1+3=4, cost=10.0×4=40.0. (1,2): ratios=10.0, 10.0, max=10.0, sum_qualities=2+3=5, cost=10.0×5=50.0. Step 3: Minimum cost = min(30.0, 40.0, 50.0) = 30.0."
    }
  ],
  "approaches": [
    {
      "id": "brute-force-combinations",
      "name": "Brute Force O(n! / (k!(n-k)!))",
      "summary": "Generate all combinations of k workers from n, compute the cost for each combination based on wage and quality ratios, and track the minimum. This is straightforward but impractical for large n due to exponential growth.",
      "timeComplexity": "O(C(n, k) * k)",
      "spaceComplexity": "O(k)",
      "ladders": [
        {
          "level": 0,
          "title": "Full Problem — Brute Force Minimum Cost to Hire K Workers",
          "desc": "Generate all combinations of k workers from n, compute cost for each based on wage/quality ratios, and track minimum.",
          "explanation": {
            "prose": "This brute force approach directly implements the problem requirements by exploring every possible hiring combination. The intuition is that we need to hire exactly k workers, and the cost is determined by the highest wage-to-quality ratio among selected workers multiplied by the sum of their qualities. By checking all possible combinations, we guarantee finding the optimal solution. The algorithm works by: 1) Generating all combinations of k workers from n using combinatorial generation, 2) For each combination, finding the maximum wage/quality ratio among selected workers, 3) Calculating total cost as max_ratio × sum of qualities of selected workers, 4) Tracking the minimum cost across all combinations.",
            "connectsTo": {
              "level": "L1",
              "reason": "by using the combination generation as the key subroutine"
            },
            "timeComplexity": {
              "value": "O(C(n,k)",
              "note": "× k) where C(n,k) is binomial coefficient, as we process k workers for each combination"
            },
            "spaceComplexity": {
              "value": "O(k)",
              "note": "for storing current combination"
            },
            "commonMistakes": [
              "forgetting to use the maximum ratio for cost calculation",
              "incorrectly handling floating-point precision",
              "not considering all combinations"
            ],
            "codePattern": "generate combinations recursively or iteratively, compute max ratio and quality sum for each, track minimum",
            "algorithm": null,
            "summary": null
          },
          "examples": [
            {
              "input": "n=4, wages=[70,50,30,80], qualities=[10,20,5,15], k=2",
              "output": "105.0",
              "trace": "Step 1: Generate all C(4,2)=6 combinations: (0,1), (0,2), (0,3), (1,2), (1,3), (2,3). Step 2: For each combination: (0,1): ratios=70/10=7.0, 50/20=2.5, max=7.0, sum_qualities=10+20=30, cost=7.0×30=210.0. (0,2): ratios=7.0, 30/5=6.0, max=7.0, sum_qualities=10+5=15, cost=7.0×15=105.0. (0,3): ratios=7.0, 80/15≈5.33, max=7.0, sum_qualities=10+15=25, cost=7.0×25=175.0. (1,2): ratios=2.5, 6.0, max=6.0, sum_qualities=20+5=25, cost=6.0×25=150.0. (1,3): ratios=2.5, 5.33, max=5.33, sum_qualities=20+15=35, cost=5.33×35≈186.67. (2,3): ratios=6.0, 5.33, max=6.0, sum_qualities=5+15=20, cost=6.0×20=120.0. Step 3: Minimum cost = min(210.0, 105.0, 175.0, 150.0, 186.67, 120.0) = 105.0."
            },
            {
              "input": "n=3, wages=[10,20,30], qualities=[1,2,3], k=2",
              "output": "30.0",
              "trace": "Step 1: Generate all C(3,2)=3 combinations: (0,1), (0,2), (1,2). Step 2: For each combination: (0,1): ratios=10/1=10.0, 20/2=10.0, max=10.0, sum_qualities=1+2=3, cost=10.0×3=30.0. (0,2): ratios=10.0, 30/3=10.0, max=10.0, sum_qualities=1+3=4, cost=10.0×4=40.0. (1,2): ratios=10.0, 10.0, max=10.0, sum_qualities=2+3=5, cost=10.0×5=50.0. Step 3: Minimum cost = min(30.0, 40.0, 50.0) = 30.0."
            }
          ],
          "testCases": [
            {
              "input": "n=4, wages=[70,50,30,80], qualities=[10,20,5,15], k=2",
              "expected": "105.0"
            },
            {
              "input": "n=3, wages=[10,20,30], qualities=[1,2,3], k=2",
              "expected": "30.0"
            },
            {
              "input": "n=5, wages=[3,1,10,2,8], qualities=[3,1,5,2,4], k=3",
              "expected": "25.0"
            },
            {
              "input": "n=2, wages=[15,25], qualities=[3,5], k=1",
              "expected": "5.0"
            },
            {
              "input": "n=2, wages=[15,25], qualities=[3,5], k=2",
              "expected": "40.0"
            },
            {
              "input": "n=3, wages=[100,200,300], qualities=[10,20,30], k=1",
              "expected": "10.0"
            },
            {
              "input": "n=3, wages=[100,200,300], qualities=[10,20,30], k=3",
              "expected": "600.0"
            },
            {
              "input": "n=4, wages=[10,20,30,40], qualities=[1,1,1,1], k=2",
              "expected": "30.0"
            },
            {
              "input": "n=4, wages=[10,20,30,40], qualities=[1,2,3,4], k=2",
              "expected": "25.0"
            },
            {
              "input": "n=1, wages=[50], qualities=[5], k=1",
              "expected": "50.0"
            }
          ]
        },
        {
          "level": 1,
          "title": "Key Sub-routine — Generate All Combinations of K Elements from N",
          "desc": "Generate all possible subsets of size k from n elements using combinatorial generation.",
          "explanation": {
            "prose": "This subroutine is the core of the brute force approach, as it systematically explores all possible hiring combinations. The intuition is that to find the optimal k workers, we must consider every possible group of k workers from the total n. The algorithm typically uses recursion or iteration to build combinations: start with an empty combination, add elements one by one, backtrack when reaching size k, and continue until all combinations are generated. Step-by-step: 1) Initialize an empty list for current combination and results, 2) Define recursive function that takes start index, 3) If current combination size equals k, add copy to results, 4) Otherwise, iterate from start to n, add element, recurse with next index, remove element (backtrack). This feeds into L0 by providing the combinations to evaluate for cost.",
            "connectsTo": null,
            "timeComplexity": {
              "value": "O(C(n,k)",
              "note": ") to generate all combinations, space complexity is O(k) for recursion depth and current combination"
            },
            "spaceComplexity": null,
            "commonMistakes": [
              "not copying combinations before storing (leading to reference issues)",
              "incorrect indexing causing duplicates",
              "inefficient generation for large n"
            ],
            "codePattern": "use recursion with backtracking or iterative methods like bit manipulation for small n",
            "algorithm": null,
            "summary": null
          },
          "examples": [
            {
              "input": "n=4, k=2",
              "output": "[(0,1), (0,2), (0,3), (1,2), (1,3), (2,3)]",
              "trace": "Step 1: Start with empty combination [], start=0. Step 2: Add 0: [0], start=1. Step 3: Add 1: [0,1] size=2 → store [0,1]. Backtrack: remove 1 → [0]. Step 4: Add 2: [0,2] size=2 → store [0,2]. Backtrack: remove 2 → [0]. Step 5: Add 3: [0,3] size=2 → store [0,3]. Backtrack: remove 3 → [0], then remove 0 → []. Step 6: Add 1: [1], start=2. Step 7: Add 2: [1,2] size=2 → store [1,2]. Backtrack: remove 2 → [1]. Step 8: Add 3: [1,3] size=2 → store [1,3]. Backtrack: remove 3 → [1], then remove 1 → []. Step 9: Add 2: [2], start=3. Step 10: Add 3: [2,3] size=2 → store [2,3]. Done."
            },
            {
              "input": "n=3, k=1",
              "output": "[(0), (1), (2)]",
              "trace": "Step 1: Start with empty combination [], start=0. Step 2: Add 0: [0] size=1 → store [0]. Backtrack: remove 0 → []. Step 3: Add 1: [1] size=1 → store [1]. Backtrack: remove 1 → []. Step 4: Add 2: [2] size=1 → store [2]. Done."
            }
          ],
          "testCases": [
            {
              "input": "n=4, k=2",
              "expected": "[(0,1), (0,2), (0,3), (1,2), (1,3), (2,3)]"
            },
            {
              "input": "n=3, k=1",
              "expected": "[(0), (1), (2)]"
            },
            {
              "input": "n=5, k=3",
              "expected": "[(0,1,2), (0,1,3), (0,1,4), (0,2,3), (0,2,4), (0,3,4), (1,2,3), (1,2,4), (1,3,4), (2,3,4)]"
            },
            {
              "input": "n=2, k=2",
              "expected": "[(0,1)]"
            },
            {
              "input": "n=2, k=1",
              "expected": "[(0), (1)]"
            },
            {
              "input": "n=3, k=3",
              "expected": "[(0,1,2)]"
            },
            {
              "input": "n=4, k=4",
              "expected": "[(0,1,2,3)]"
            },
            {
              "input": "n=4, k=0",
              "expected": "[()]"
            },
            {
              "input": "n=0, k=0",
              "expected": "[()]"
            },
            {
              "input": "n=3, k=2",
              "expected": "[(0,1), (0,2), (1,2)]"
            }
          ]
        },
        {
          "level": 2,
          "title": "Core Logic — Compute Cost for a Worker Combination Using Wage/Quality Ratios",
          "desc": "Given a combination of workers with wages and qualities, calculate the hiring cost based on the maximum ratio rule.",
          "explanation": {
            "prose": "This core logic implements the cost calculation that defines the problem. The intuition is that when hiring multiple workers, you must pay each at least their demanded wage, which is proportional to their quality via a ratio. To minimize cost while satisfying all wages, you choose the highest wage-to-quality ratio among selected workers as the pay rate, then multiply by total quality. This ensures each worker gets at least their wage: if ratio = wage/quality, then pay = ratio × quality ≥ wage.",
            "connectsTo": {
              "level": "L1",
              "reason": "by being applied to each generated combination"
            },
            "timeComplexity": {
              "value": "O(k)",
              "note": "for k workers, space O(1)"
            },
            "spaceComplexity": null,
            "commonMistakes": [
              "using average instead of maximum ratio (incorrect)",
              "forgetting floating-point division",
              "not handling zero quality (though problem assumes positive)"
            ],
            "codePattern": "iterate through combination indices, compute ratios, track max, sum qualities, return product",
            "algorithm": [
              "1) For each worker in the combination, compute ratio = wage/quality,",
              "2) Find maximum ratio,",
              "3) Sum qualities of all workers in combination,",
              "4) Cost = max_ratio × sum_qualities."
            ],
            "summary": null
          },
          "examples": [
            {
              "input": "combination=(0,2), wages=[70,50,30,80], qualities=[10,20,5,15]",
              "output": "105.0",
              "trace": "Step 1: Workers indices 0 and 2. Step 2: Compute ratios: worker0: 70/10=7.0, worker2: 30/5=6.0. Step 3: Max ratio = max(7.0, 6.0)=7.0. Step 4: Sum qualities = 10+5=15. Step 5: Cost = 7.0×15=105.0."
            },
            {
              "input": "combination=(1,3), wages=[10,20,30,40], qualities=[1,2,3,4]",
              "output": "50.0",
              "trace": "Step 1: Workers indices 1 and 3. Step 2: Compute ratios: worker1: 20/2=10.0, worker3: 40/4=10.0. Step 3: Max ratio = max(10.0, 10.0)=10.0. Step 4: Sum qualities = 2+4=6. Step 5: Cost = 10.0×6=60.0. Wait, check: 10.0×6=60.0, but expected 50.0? Let's recompute: wages[1]=20, qualities[1]=2, ratio=10.0; wages[3]=40, qualities[3]=4, ratio=10.0; max=10.0; sum=2+4=6; cost=10.0×6=60.0. Actually, my example input might be inconsistent; for clarity, use wages=[10,20,30,40], qualities=[1,2,3,4], then cost=60.0. To match expected 50.0, adjust: wages=[10,15,30,35], qualities=[1,2,3,4], combination=(1,3): ratios=15/2=7.5, 35/4=8.75, max=8.75, sum=2+4=6, cost=8.75×6=52.5. Hmm, let's use exact: wages=[10,20,30,40], qualities=[1,2,3,4], output should be 60.0. I'll correct: input wages=[10,20,30,40], qualities=[1,2,3,4], output 60.0."
            }
          ],
          "testCases": [
            {
              "input": "combination=(0,1), wages=[70,50,30,80], qualities=[10,20,5,15]",
              "expected": "210.0"
            },
            {
              "input": "combination=(0,2), wages=[70,50,30,80], qualities=[10,20,5,15]",
              "expected": "105.0"
            },
            {
              "input": "combination=(1,2), wages=[10,20,30], qualities=[1,2,3]",
              "expected": "50.0"
            },
            {
              "input": "combination=(0), wages=[50], qualities=[5]",
              "expected": "50.0"
            },
            {
              "input": "combination=(0,1,2), wages=[3,1,10,2,8], qualities=[3,1,5,2,4]",
              "expected": "25.0"
            },
            {
              "input": "combination=(0,1), wages=[15,25], qualities=[3,5]",
              "expected": "40.0"
            },
            {
              "input": "combination=(0), wages=[100], qualities=[10]",
              "expected": "100.0"
            },
            {
              "input": "combination=(0,1), wages=[10,20], qualities=[1,1]",
              "expected": "40.0"
            },
            {
              "input": "combination=(0,2), wages=[10,20,30], qualities=[1,2,3]",
              "expected": "40.0"
            },
            {
              "input": "combination=(1,3), wages=[10,20,30,40], qualities=[1,2,3,4]",
              "expected": "60.0"
            }
          ]
        },
        {
          "level": 3,
          "title": "Building Block — Find Maximum Value in a List",
          "desc": "Given a list of numbers, identify the maximum value.",
          "explanation": {
            "prose": "This building block is essential for determining the highest wage-to-quality ratio in a combination. The intuition is straightforward: to apply the maximum ratio rule, we need to find the largest value among computed ratios. The algorithm iterates through the list, keeping track of the largest value seen so far: initialize max_val to the first element or negative infinity, then for each element, if it's greater than max_val, update max_val.",
            "connectsTo": {
              "level": "L2",
              "reason": "by being used in the cost calculation to find max ratio"
            },
            "timeComplexity": {
              "value": "O(n)",
              "note": "for n elements, space O(1)"
            },
            "spaceComplexity": null,
            "commonMistakes": [
              "not handling empty lists",
              "initializing incorrectly",
              "using inefficient methods like sorting"
            ],
            "codePattern": "simple loop with comparison",
            "algorithm": null,
            "summary": null
          },
          "examples": [
            {
              "input": "list=[7.0, 2.5, 6.0, 5.33]",
              "output": "7.0",
              "trace": "Step 1: Initialize max_val = first element = 7.0. Step 2: Check 2.5: 2.5 < 7.0, max_val remains 7.0. Step 3: Check 6.0: 6.0 < 7.0, max_val remains 7.0. Step 4: Check 5.33: 5.33 < 7.0, max_val remains 7.0. Step 5: Return 7.0."
            },
            {
              "input": "list=[10.0, 10.0, 10.0]",
              "output": "10.0",
              "trace": "Step 1: Initialize max_val = 10.0. Step 2: Check second 10.0: equal, max_val remains 10.0. Step 3: Check third 10.0: equal, max_val remains 10.0. Step 4: Return 10.0."
            }
          ],
          "testCases": [
            {
              "input": "list=[7.0, 2.5, 6.0, 5.33]",
              "expected": "7.0"
            },
            {
              "input": "list=[10.0, 10.0, 10.0]",
              "expected": "10.0"
            },
            {
              "input": "list=[1.5, 3.2, 0.8]",
              "expected": "3.2"
            },
            {
              "input": "list=[-5, -10, -3]",
              "expected": "-3"
            },
            {
              "input": "list=[100]",
              "expected": "100"
            },
            {
              "input": "list=[0, 0, 0]",
              "expected": "0"
            },
            {
              "input": "list=[2.718, 3.141, 1.618]",
              "expected": "3.141"
            },
            {
              "input": "list=[7, 5, 9, 2]",
              "expected": "9"
            },
            {
              "input": "list=[1.1, 1.01, 1.001]",
              "expected": "1.1"
            },
            {
              "input": "list=[-1.5, -2.5, -0.5]",
              "expected": "-0.5"
            }
          ]
        },
        {
          "level": 4,
          "title": "Basic Operation — Compute Wage-to-Quality Ratio",
          "desc": "Divide wage by quality for a worker to get the pay rate per unit quality.",
          "explanation": {
            "prose": "This basic operation computes the fundamental ratio that drives the cost calculation. The intuition is that each worker's wage demand is proportional to their quality, and this ratio represents how much must be paid per unit of quality to meet their wage. Mathematically, ratio = wage / quality. The algorithm is a simple division: take two positive numbers (wage and quality) and return their quotient. Time and space complexity are O(1).",
            "connectsTo": {
              "level": "L3",
              "reason": "by providing the values for which we find the maximum"
            },
            "timeComplexity": null,
            "spaceComplexity": null,
            "commonMistakes": [
              "division by zero (quality is positive in problem)",
              "floating-point precision issues",
              "incorrect order of operands"
            ],
            "codePattern": "direct division operation",
            "algorithm": null,
            "summary": null
          },
          "examples": [
            {
              "input": "wage=70, quality=10",
              "output": "7.0",
              "trace": "Step 1: Compute 70 / 10. Step 2: Result = 7.0."
            },
            {
              "input": "wage=30, quality=5",
              "output": "6.0",
              "trace": "Step 1: Compute 30 / 5. Step 2: Result = 6.0."
            }
          ],
          "testCases": [
            {
              "input": "wage=70, quality=10",
              "expected": "7.0"
            },
            {
              "input": "wage=30, quality=5",
              "expected": "6.0"
            },
            {
              "input": "wage=50, quality=20",
              "expected": "2.5"
            },
            {
              "input": "wage=10, quality=1",
              "expected": "10.0"
            },
            {
              "input": "wage=20, quality=2",
              "expected": "10.0"
            },
            {
              "input": "wage=100, quality=10",
              "expected": "10.0"
            },
            {
              "input": "wage=15, quality=3",
              "expected": "5.0"
            },
            {
              "input": "wage=25, quality=5",
              "expected": "5.0"
            },
            {
              "input": "wage=40, quality=4",
              "expected": "10.0"
            },
            {
              "input": "wage=80, quality=15",
              "expected": "5.333333333333333"
            }
          ]
        },
        {
          "level": 5,
          "title": "Concept Foundation — Division of Two Numbers",
          "desc": "Perform basic arithmetic division: a / b.",
          "explanation": {
            "prose": "This is the simplest prerequisite concept, fundamental to computing ratios. Division is the operation of splitting a number (dividend) into equal parts specified by another number (divisor). Intuition: if you have a total wage and a quality measure, dividing gives the wage per unit quality. The algorithm: given two numbers a and b (b ≠ 0), compute quotient = a / b. For integers, result may be float if not divisible evenly. Time and space O(1).",
            "connectsTo": {
              "level": "L4",
              "reason": "as the operation used to compute wage/quality ratio"
            },
            "timeComplexity": null,
            "spaceComplexity": null,
            "commonMistakes": [
              "dividing by zero",
              "misunderstanding integer vs float division in programming",
              "precision errors with floating-point"
            ],
            "codePattern": "use division operator '/'",
            "algorithm": null,
            "summary": null
          },
          "examples": [
            {
              "input": "a=10, b=2",
              "output": "5.0",
              "trace": "Step 1: Compute 10 divided by 2. Step 2: Result = 5.0."
            },
            {
              "input": "a=7, b=3",
              "output": "2.3333333333333335",
              "trace": "Step 1: Compute 7 divided by 3. Step 2: Result ≈ 2.3333333333333335."
            }
          ],
          "testCases": [
            {
              "input": "a=10, b=2",
              "expected": "5.0"
            },
            {
              "input": "a=7, b=3",
              "expected": "2.3333333333333335"
            },
            {
              "input": "a=15, b=5",
              "expected": "3.0"
            },
            {
              "input": "a=100, b=10",
              "expected": "10.0"
            },
            {
              "input": "a=1, b=4",
              "expected": "0.25"
            },
            {
              "input": "a=0, b=5",
              "expected": "0.0"
            },
            {
              "input": "a=8, b=2",
              "expected": "4.0"
            },
            {
              "input": "a=9, b=6",
              "expected": "1.5"
            },
            {
              "input": "a=20, b=4",
              "expected": "5.0"
            },
            {
              "input": "a=3, b=7",
              "expected": "0.42857142857142855"
            }
          ]
        }
      ]
    },
    {
      "id": "greedy-with-sorting-and-heap",
      "name": "Greedy with Sorting and Max-Heap O(n log n)",
      "summary": "Sort workers by wage-to-quality ratio, use a max-heap to maintain the k smallest qualities as you iterate, and compute cost based on the current ratio and total quality. This leverages the fact that cost is determined by the highest ratio in the selected group.",
      "timeComplexity": "O(n log n)",
      "spaceComplexity": "O(n)",
      "ladders": [
        {
          "level": 0,
          "title": "Full Problem — Minimum Cost to Hire K Workers with Greedy Approach",
          "desc": "Complete solution using sorting by wage-to-quality ratio and a max-heap to track k smallest qualities.",
          "explanation": {
            "prose": "The problem requires hiring exactly k workers where each worker must be paid at least their expected wage, and wages are proportional to quality. The key insight is that if we select k workers, the total cost is determined by the highest wage-to-quality ratio among them multiplied by the sum of their qualities. This is because all workers must be paid proportionally to quality at the same ratio. The greedy approach sorts all workers by their ratio in ascending order. As we iterate through this sorted list, we maintain a max-heap of the k smallest qualities seen so far. For each worker, we add their quality to the heap and if the heap size exceeds k, we remove the largest quality (to keep the k smallest). We then compute the cost as the current worker's ratio multiplied by the sum of qualities in the heap (which are the k smallest qualities up to this point). The minimum cost across all iterations is the answer. This works because by sorting by ratio, we ensure that the current worker's ratio is the maximum among the selected k workers, satisfying the wage constraint. Keeping the k smallest qualities minimizes the sum, thus minimizing the cost.",
            "connectsTo": null,
            "timeComplexity": {
              "value": "O(n log n)",
              "note": "for sorting plus O(n log k) for heap operations, overall O(n log n)"
            },
            "spaceComplexity": {
              "value": "O(n)",
              "note": "for storing workers and the heap"
            },
            "commonMistakes": null,
            "codePattern": null,
            "algorithm": null,
            "summary": null
          },
          "examples": [
            {
              "input": "quality = [10, 20, 5], wage = [70, 50, 30], k = 2",
              "output": "105.0",
              "trace": "Step 1: Compute ratios: worker0: 70/10=7.0, worker1: 50/20=2.5, worker2: 30/5=6.0. Step 2: Sort workers by ratio: [(1, 2.5, 20), (2, 6.0, 5), (0, 7.0, 10)]. Step 3: Initialize max-heap, total_quality=0, min_cost=inf. Step 4: Iterate: i=0, ratio=2.5, quality=20, push 20 to heap, total_quality=20, heap size=1 < k=2, continue. i=1, ratio=6.0, quality=5, push 5 to heap, total_quality=25, heap size=2 == k, cost=6.0*25=150.0, min_cost=150.0. i=2, ratio=7.0, quality=10, push 10 to heap, total_quality=35, heap size=3 > k, pop largest quality 20, total_quality=15, cost=7.0*15=105.0, min_cost=105.0. Step 5: Return min_cost=105.0."
            },
            {
              "input": "quality = [3, 1, 10, 10, 1], wage = [4, 8, 2, 2, 7], k = 3",
              "output": "30.666666666666664",
              "trace": "Step 1: Compute ratios: worker0: 4/3≈1.333, worker1: 8/1=8.0, worker2: 2/10=0.2, worker3: 2/10=0.2, worker4: 7/1=7.0. Step 2: Sort workers by ratio: [(2, 0.2, 10), (3, 0.2, 10), (0, 1.333, 3), (4, 7.0, 1), (1, 8.0, 1)]. Step 3: Initialize heap, total_quality=0, min_cost=inf. Step 4: Iterate: i=0, ratio=0.2, quality=10, push 10, total_quality=10, size=1 < 3. i=1, ratio=0.2, quality=10, push 10, total_quality=20, size=2 < 3. i=2, ratio=1.333, quality=3, push 3, total_quality=23, size=3 == k, cost=1.333*23≈30.666, min_cost=30.666. i=3, ratio=7.0, quality=1, push 1, total_quality=24, size=4 > k, pop largest 10, total_quality=14, cost=7.0*14=98.0, min_cost=30.666. i=4, ratio=8.0, quality=1, push 1, total_quality=15, size=4 > k, pop largest 10, total_quality=5, cost=8.0*5=40.0, min_cost=30.666. Step 5: Return min_cost≈30.666."
            }
          ],
          "testCases": [
            {
              "input": "quality = [10], wage = [100], k = 1",
              "expected": "100.0"
            },
            {
              "input": "quality = [10, 20], wage = [50, 100], k = 1",
              "expected": "50.0"
            },
            {
              "input": "quality = [10, 20], wage = [50, 100], k = 2",
              "expected": "150.0"
            },
            {
              "input": "quality = [3, 1, 10], wage = [4, 8, 2], k = 2",
              "expected": "16.0"
            },
            {
              "input": "quality = [5, 5, 5], wage = [10, 20, 30], k = 2",
              "expected": "40.0"
            },
            {
              "input": "quality = [1, 2, 3, 4], wage = [1, 2, 3, 4], k = 3",
              "expected": "9.0"
            },
            {
              "input": "quality = [100, 200, 300], wage = [50, 100, 150], k = 2",
              "expected": "250.0"
            },
            {
              "input": "quality = [2, 4, 6], wage = [6, 12, 18], k = 3",
              "expected": "36.0"
            },
            {
              "input": "quality = [1, 1, 1, 1], wage = [10, 20, 30, 40], k = 2",
              "expected": "30.0"
            },
            {
              "input": "quality = [5, 10, 15], wage = [20, 30, 40], k = 2",
              "expected": "60.0"
            }
          ]
        },
        {
          "level": 1,
          "title": "Key Sub-routine — Maintaining K Smallest Qualities with Max-Heap",
          "desc": "Implement a function to track the k smallest elements in a stream using a max-heap.",
          "explanation": {
            "prose": "This sub-routine is crucial because it efficiently maintains the k smallest qualities as we iterate through workers sorted by ratio, minimizing the total quality sum for cost calculation. The intuition is that a max-heap allows quick access to the largest element among the k smallest, so when a new quality is added, if it's smaller than the current largest, we replace the largest with the new one. This ensures the heap always contains the k smallest qualities seen so far. The algorithm: initialize an empty max-heap (using negative values in languages with min-heap default). For each new quality, push it onto the heap. If the heap size exceeds k, pop the largest element (which is at the root). Keep a running sum of qualities in the heap by adding the new quality and subtracting the popped one if applicable. This runs in O(log k) per operation.",
            "connectsTo": {
              "level": "L0",
              "reason": "This subroutine is called for each worker in the sorted list to update the selected qualities"
            },
            "timeComplexity": null,
            "spaceComplexity": null,
            "commonMistakes": [
              "not handling the heap as max-heap correctly",
              "forgetting to update the total quality sum when popping"
            ],
            "codePattern": "use heapq in Python with negative values for max-heap",
            "algorithm": null,
            "summary": null
          },
          "examples": [
            {
              "input": "qualities = [20, 5, 10], k = 2",
              "output": "heap = [5, 10], total_quality = 15",
              "trace": "Step 1: Initialize max-heap as empty list, total_quality=0. Step 2: Add 20: push -20, heap=[-20], total_quality=20, size=1 <= k=2. Step 3: Add 5: push -5, heap=[-20, -5], total_quality=25, size=2 == k. Step 4: Add 10: push -10, heap=[-20, -5, -10], size=3 > k, pop largest: -20 (value 20), heap=[-10, -5], total_quality=25-20+10=15. Final heap values: 5 and 10, total_quality=15."
            },
            {
              "input": "qualities = [3, 1, 4, 2], k = 3",
              "output": "heap = [1, 2, 3], total_quality = 6",
              "trace": "Step 1: Initialize heap=[], total=0. Step 2: Add 3: push -3, heap=[-3], total=3, size=1. Step 3: Add 1: push -1, heap=[-3, -1], total=4, size=2. Step 4: Add 4: push -4, heap=[-4, -1, -3], total=8, size=3 == k. Step 5: Add 2: push -2, heap=[-4, -2, -3, -1], size=4 > k, pop largest: -4 (value 4), heap=[-3, -2, -1], total=8-4+2=6. Final heap values: 1,2,3, total=6."
            }
          ],
          "testCases": [
            {
              "input": "qualities = [5], k = 1",
              "expected": "heap = [5], total = 5"
            },
            {
              "input": "qualities = [10, 20], k = 1",
              "expected": "heap = [10], total = 10"
            },
            {
              "input": "qualities = [10, 5, 20], k = 2",
              "expected": "heap = [5, 10], total = 15"
            },
            {
              "input": "qualities = [1, 2, 3, 4], k = 3",
              "expected": "heap = [1, 2, 3], total = 6"
            },
            {
              "input": "qualities = [100, 50, 75], k = 2",
              "expected": "heap = [50, 75], total = 125"
            },
            {
              "input": "qualities = [3, 1, 4, 1, 5], k = 3",
              "expected": "heap = [1, 1, 3], total = 5"
            },
            {
              "input": "qualities = [6, 2, 8, 4], k = 2",
              "expected": "heap = [2, 4], total = 6"
            },
            {
              "input": "qualities = [7, 3, 9, 1], k = 1",
              "expected": "heap = [1], total = 1"
            },
            {
              "input": "qualities = [5, 5, 5, 5], k = 3",
              "expected": "heap = [5, 5, 5], total = 15"
            },
            {
              "input": "qualities = [10, 9, 8, 7, 6], k = 4",
              "expected": "heap = [6, 7, 8, 9], total = 30"
            }
          ]
        },
        {
          "level": 2,
          "title": "Core Logic — Sorting by Wage-to-Quality Ratio for Cost Minimization",
          "desc": "Understand why sorting workers by ratio allows greedy selection of the optimal group.",
          "explanation": {
            "prose": "The core logic hinges on the mathematical property that when hiring k workers, the total cost equals the maximum wage-to-quality ratio among them multiplied by the sum of their qualities. This is because all workers must be paid at the same ratio to maintain proportionality. By sorting workers in ascending order of their ratio, we ensure that as we iterate, the current worker's ratio is the largest among any potential group of k workers that includes them. This allows us to fix the ratio and focus on minimizing the sum of qualities. For each worker in the sorted list, we consider them as the 'captain' with the highest ratio, and we select the k-1 other workers with the smallest qualities from those seen so far (using the max-heap from L1). This greedy choice is optimal because if we choose a different worker with a higher ratio later, the cost would increase due to the higher ratio, unless the sum of qualities decreases significantly—but by always picking the smallest qualities, we minimize the sum. The algorithm thus explores all possible captains efficiently.",
            "connectsTo": {
              "level": "L0",
              "reason": "This sorting step is done before the heap iteration"
            },
            "timeComplexity": null,
            "spaceComplexity": null,
            "commonMistakes": [
              "not understanding why the ratio must be the maximum or not sorting correctly"
            ],
            "codePattern": "create a list of (ratio, quality) tuples and sort by ratio",
            "algorithm": null,
            "summary": null
          },
          "examples": [
            {
              "input": "workers = [(70,10), (50,20), (30,5)]",
              "output": "sorted = [(50,20), (30,5), (70,10)] by ratio",
              "trace": "Step 1: Compute ratios: worker0: 70/10=7.0, worker1: 50/20=2.5, worker2: 30/5=6.0. Step 2: Create list: [(7.0,10), (2.5,20), (6.0,5)]. Step 3: Sort by first element (ratio): [(2.5,20), (6.0,5), (7.0,10)]."
            },
            {
              "input": "workers = [(4,3), (8,1), (2,10), (2,10), (7,1)]",
              "output": "sorted = [(2,10), (2,10), (4,3), (7,1), (8,1)] by ratio",
              "trace": "Step 1: Compute ratios: worker0: 4/3≈1.333, worker1: 8/1=8.0, worker2: 2/10=0.2, worker3: 2/10=0.2, worker4: 7/1=7.0. Step 2: List: [(1.333,3), (8.0,1), (0.2,10), (0.2,10), (7.0,1)]. Step 3: Sort: [(0.2,10), (0.2,10), (1.333,3), (7.0,1), (8.0,1)]."
            }
          ],
          "testCases": [
            {
              "input": "workers = [(100,10)]",
              "expected": "sorted = [(10.0,10)]"
            },
            {
              "input": "workers = [(50,10), (100,20)]",
              "expected": "sorted = [(5.0,10), (5.0,20)]"
            },
            {
              "input": "workers = [(70,10), (50,20)]",
              "expected": "sorted = [(2.5,20), (7.0,10)]"
            },
            {
              "input": "workers = [(30,5), (20,4)]",
              "expected": "sorted = [(5.0,4), (6.0,5)]"
            },
            {
              "input": "workers = [(1,1), (2,2), (3,3)]",
              "expected": "sorted = [(1.0,1), (1.0,2), (1.0,3)]"
            },
            {
              "input": "workers = [(10,2), (20,5), (30,10)]",
              "expected": "sorted = [(4.0,5), (5.0,2), (3.0,10)]"
            },
            {
              "input": "workers = [(5,1), (10,2), (15,3)]",
              "expected": "sorted = [(5.0,1), (5.0,2), (5.0,3)]"
            },
            {
              "input": "workers = [(12,3), (8,2), (20,5)]",
              "expected": "sorted = [(4.0,2), (4.0,3), (4.0,5)]"
            },
            {
              "input": "workers = [(6,2), (9,3), (12,4)]",
              "expected": "sorted = [(3.0,2), (3.0,3), (3.0,4)]"
            },
            {
              "input": "workers = [(100,50), (200,100)]",
              "expected": "sorted = [(2.0,50), (2.0,100)]"
            }
          ]
        },
        {
          "level": 3,
          "title": "Building Block — Computing Wage-to-Quality Ratio and Understanding Proportional Pay",
          "desc": "Calculate ratio for each worker and grasp why cost depends on the maximum ratio.",
          "explanation": {
            "prose": "This building block involves computing the wage-to-quality ratio for each worker, defined as wage[i] / quality[i]. This ratio represents how much must be paid per unit of quality for that worker. The fundamental concept is that when hiring multiple workers, they must be paid in proportion to their quality to maintain fairness, meaning if worker A has quality 10 and worker B has quality 20, and we decide on a pay ratio R, then A gets paid 10*R and B gets paid 20*R. The constraint is that each worker must be paid at least their expected wage, so for a selected group, the ratio R must be at least the maximum of the individual workers' ratios. Thus, the total cost for k workers is max_ratio * sum(qualities). This insight reduces the problem to finding a group where max_ratio * sum(qualities) is minimized.",
            "connectsTo": {
              "level": "L2",
              "reason": "These ratios are used for sorting"
            },
            "timeComplexity": null,
            "spaceComplexity": null,
            "commonMistakes": [
              "using integer division instead of float or not understanding the proportionality rule"
            ],
            "codePattern": "iterate through arrays, compute float(wage[i])/quality[i], and store pairs",
            "algorithm": null,
            "summary": null
          },
          "examples": [
            {
              "input": "wage = [70, 50, 30], quality = [10, 20, 5]",
              "output": "ratios = [7.0, 2.5, 6.0]",
              "trace": "Step 1: For worker0: 70/10 = 7.0. Step 2: For worker1: 50/20 = 2.5. Step 3: For worker2: 30/5 = 6.0. Result: [7.0, 2.5, 6.0]."
            },
            {
              "input": "wage = [4, 8, 2, 2, 7], quality = [3, 1, 10, 10, 1]",
              "output": "ratios = [1.333..., 8.0, 0.2, 0.2, 7.0]",
              "trace": "Step 1: worker0: 4/3 ≈ 1.333. Step 2: worker1: 8/1 = 8.0. Step 3: worker2: 2/10 = 0.2. Step 4: worker3: 2/10 = 0.2. Step 5: worker4: 7/1 = 7.0. Result: [1.333, 8.0, 0.2, 0.2, 7.0]."
            }
          ],
          "testCases": [
            {
              "input": "wage = [100], quality = [10]",
              "expected": "[10.0]"
            },
            {
              "input": "wage = [50, 100], quality = [10, 20]",
              "expected": "[5.0, 5.0]"
            },
            {
              "input": "wage = [70, 50], quality = [10, 20]",
              "expected": "[7.0, 2.5]"
            },
            {
              "input": "wage = [30, 20], quality = [5, 4]",
              "expected": "[6.0, 5.0]"
            },
            {
              "input": "wage = [1, 2, 3], quality = [1, 2, 3]",
              "expected": "[1.0, 1.0, 1.0]"
            },
            {
              "input": "wage = [10, 20, 30], quality = [2, 5, 10]",
              "expected": "[5.0, 4.0, 3.0]"
            },
            {
              "input": "wage = [5, 10, 15], quality = [1, 2, 3]",
              "expected": "[5.0, 5.0, 5.0]"
            },
            {
              "input": "wage = [12, 8, 20], quality = [3, 2, 5]",
              "expected": "[4.0, 4.0, 4.0]"
            },
            {
              "input": "wage = [6, 9, 12], quality = [2, 3, 4]",
              "expected": "[3.0, 3.0, 3.0]"
            },
            {
              "input": "wage = [100, 200], quality = [50, 100]",
              "expected": "[2.0, 2.0]"
            }
          ]
        },
        {
          "level": 4,
          "title": "Basic Operation — Using a Max-Heap to Track Largest Elements",
          "desc": "Implement a max-heap data structure to efficiently find and remove the maximum element.",
          "explanation": {
            "prose": "A max-heap is a complete binary tree where each node is greater than or equal to its children, allowing O(1) access to the maximum element and O(log n) insertion and deletion. In this context, we use it to maintain the k smallest qualities by storing negatives in a min-heap (since many libraries provide min-heap by default). The basic operations are: push (add an element), pop (remove the maximum), and peek (view the maximum without removing). For tracking k smallest, we push each new quality as a negative value onto a min-heap, so the smallest negative (i.e., the largest positive quality) is at the root. If the heap size exceeds k, we pop the root to remove the largest quality, ensuring we keep only the k smallest. This operation is key for efficiency.",
            "connectsTo": {
              "level": "L1",
              "reason": "This is the underlying mechanism for the subroutine"
            },
            "timeComplexity": null,
            "spaceComplexity": null,
            "commonMistakes": [
              "not negating values correctly",
              "mishandling heap operations"
            ],
            "codePattern": "in Python, use heapq",
            "algorithm": null,
            "summary": null
          },
          "examples": [
            {
              "input": "operations: push 10, push 5, push 20, pop max, push 15 on empty max-heap",
              "output": "heap after ops: [15, 5, 10] (max-heap order)",
              "trace": "Step 1: Initialize heap as empty list. Step 2: Push 10: add -10, heap=[-10]. Step 3: Push 5: add -5, heap=[-10, -5]. Step 4: Push 20: add -20, heap=[-20, -5, -10]. Step 5: Pop max: remove -20 (value 20), heap=[-10, -5]. Step 6: Push 15: add -15, heap=[-15, -5, -10]. Final heap values (negated): 15, 5, 10."
            },
            {
              "input": "operations: push 3, push 1, push 4, push 2, pop max, pop max on empty max-heap",
              "output": "heap after ops: [2, 1]",
              "trace": "Step 1: Start heap=[]. Step 2: Push 3: add -3, heap=[-3]. Step 3: Push 1: add -1, heap=[-3, -1]. Step 4: Push 4: add -4, heap=[-4, -1, -3]. Step 5: Push 2: add -2, heap=[-4, -2, -3, -1]. Step 6: Pop max: remove -4 (value 4), heap=[-3, -2, -1]. Step 7: Pop max: remove -3 (value 3), heap=[-2, -1]. Final values: 2, 1."
            }
          ],
          "testCases": [
            {
              "input": "push 5, pop max on empty",
              "expected": "heap after: [], popped: 5"
            },
            {
              "input": "push 10, push 20, pop max",
              "expected": "heap after: [10], popped: 20"
            },
            {
              "input": "push 5, push 3, push 7, pop max",
              "expected": "heap after: [5, 3], popped: 7"
            },
            {
              "input": "push 1, push 2, push 3, pop max, pop max",
              "expected": "heap after: [1], popped: 3 then 2"
            },
            {
              "input": "push 100, push 50, push 75, pop max, push 25",
              "expected": "heap after: [75, 25, 50]"
            },
            {
              "input": "push 6, push 2, push 8, push 4, pop max, pop max",
              "expected": "heap after: [4, 2], popped: 8 then 6"
            },
            {
              "input": "push 7, push 3, push 9, push 1, pop max",
              "expected": "heap after: [7, 3, 1], popped: 9"
            },
            {
              "input": "push 5, push 5, push 5, pop max",
              "expected": "heap after: [5, 5], popped: 5"
            },
            {
              "input": "push 10, push 9, push 8, push 7, push 6, pop max, pop max",
              "expected": "heap after: [8, 7, 6, 9], popped: 10 then 9"
            },
            {
              "input": "push 1, pop max, push 2, pop max",
              "expected": "heap after: [], popped: 1 then 2"
            }
          ]
        },
        {
          "level": 5,
          "title": "Concept Foundation — Understanding Ratios and Proportionality",
          "desc": "Learn the basic math of ratios and how they relate to proportional relationships.",
          "explanation": {
            "prose": "A ratio is a comparison of two quantities, expressed as a fraction a/b. In this problem, the wage-to-quality ratio indicates how much wage is required per unit of quality. Proportionality means that if two quantities are proportional, they change at the same rate. For example, if worker A has quality 10 and wage 70, their ratio is 7.0. If we hire another worker B with quality 20, to pay them proportionally, we must use the same ratio, so B would get paid 20*7.0 = 140, but B's minimum wage might be different. The key rule is that when multiple workers are hired, the pay ratio must be at least the maximum of their individual ratios to satisfy all wage constraints. This foundational concept explains why the cost depends on the max ratio.",
            "connectsTo": {
              "level": "L3",
              "reason": "This understanding is necessary to compute and use ratios correctly"
            },
            "timeComplexity": null,
            "spaceComplexity": null,
            "commonMistakes": [
              "confusing ratio with difference or not grasping proportional pay"
            ],
            "codePattern": "simple division to compute ratio",
            "algorithm": null,
            "summary": null
          },
          "examples": [
            {
              "input": "Worker A: quality=10, wage=70. Worker B: quality=20, wage=50. What ratio ensures both are paid at least their wage?",
              "output": "Minimum ratio = max(70/10, 50/20) = max(7.0, 2.5) = 7.0",
              "trace": "Step 1: Compute ratio for A: 70/10 = 7.0. Step 2: Compute ratio for B: 50/20 = 2.5. Step 3: To pay proportionally, use a single ratio R. For A: pay = 10*R must be ≥ 70, so R ≥ 7.0. For B: pay = 20*R must be ≥ 50, so R ≥ 2.5. Step 4: To satisfy both, R must be at least the maximum, which is 7.0."
            },
            {
              "input": "Three workers: (quality, wage) = (5,30), (4,20), (10,20). Find the ratio for proportional pay.",
              "output": "Minimum ratio = max(30/5, 20/4, 20/10) = max(6.0, 5.0, 2.0) = 6.0",
              "trace": "Step 1: Compute ratios: worker1: 30/5=6.0, worker2: 20/4=5.0, worker3: 20/10=2.0. Step 2: For proportional pay, use ratio R. Worker1 needs 5*R ≥ 30 → R ≥ 6.0. Worker2 needs 4*R ≥ 20 → R ≥ 5.0. Worker3 needs 10*R ≥ 20 → R ≥ 2.0. Step 3: To satisfy all, R must be at least the maximum, which is 6.0."
            }
          ],
          "testCases": [
            {
              "input": "Worker: quality=1, wage=10. What is the ratio?",
              "expected": "10.0"
            },
            {
              "input": "Two workers: (5,25) and (10,50). What ratio works for both?",
              "expected": "5.0"
            },
            {
              "input": "Workers: (2,6) and (3,9). Minimum ratio?",
              "expected": "3.0"
            },
            {
              "input": "Workers: (10,70) and (20,50). Minimum ratio?",
              "expected": "7.0"
            },
            {
              "input": "Workers: (4,12) and (6,18). Minimum ratio?",
              "expected": "3.0"
            },
            {
              "input": "Workers: (8,40) and (5,30). Minimum ratio?",
              "expected": "5.0"
            },
            {
              "input": "Workers: (3,15) and (7,35). Minimum ratio?",
              "expected": "5.0"
            },
            {
              "input": "Workers: (100,500) and (200,800). Minimum ratio?",
              "expected": "5.0"
            },
            {
              "input": "Workers: (1,5) and (2,8). Minimum ratio?",
              "expected": "5.0"
            },
            {
              "input": "Workers: (6,24) and (9,36). Minimum ratio?",
              "expected": "4.0"
            }
          ]
        }
      ]
    },
    {
      "id": "dynamic-programming-with-ratios",
      "name": "Dynamic Programming O(n * k)",
      "summary": "Use DP where dp[i][j] represents the minimum cost to hire j workers from the first i workers, considering wage and quality constraints. This builds solutions incrementally but can be less efficient than the greedy approach for large n.",
      "timeComplexity": "O(n * k)",
      "spaceComplexity": "O(n * k)",
      "ladders": [
        {
          "level": 0,
          "title": "Full Problem — Minimum Cost to Hire K Workers with Dynamic Programming",
          "desc": "Complete DP solution to find minimum cost to hire exactly k workers given wage and quality constraints.",
          "explanation": {
            "prose": "The problem requires hiring exactly k workers where each worker must be paid at least their expected wage, and wages are proportional to quality. The key insight is that if we fix a worker as the 'base' (with wage-to-quality ratio r), then all other hired workers must have ratio ≤ r, and their cost is r × quality. For DP, we sort workers by wage/quality ratio, then dp[i][j] = minimum cost to hire j workers from first i workers (sorted). Transition: either skip worker i (dp[i-1][j]) or hire worker i (dp[i-1][j-1] + ratio[i] × quality[i]), but only if hiring maintains the ratio constraint (automatic due to sorting). Initialize dp[0][0]=0, others=inf. Answer is min over all dp[i][k] for i≥k. Intuition: Sorting ensures when we hire a worker i with ratio r_i, all previously hired workers have ratio ≤ r_i, so cost = r_i × sum of their qualities, but DP tracks minimum sum of qualities for each count. Actually, we need to track minimum total cost directly. Let ratio[i] = wage[i]/quality[i]. After sorting by ratio, dp[i][j] = min(dp[i-1][j], dp[i-1][j-1] + ratio[i] × quality[i]). But this is incorrect because cost for all hired workers should use the maximum ratio among them. Since sorted, maximum ratio is ratio[i] if we hire worker i. So total cost = ratio[i] × (sum of qualities of hired workers). So we need to track minimum sum of qualities for each j. Let sumQ[i][j] = minimum sum of qualities for j workers from first i. Then cost = ratio[i] × sumQ[i][j]. Transition: sumQ[i][j] = min(sumQ[i-1][j], sumQ[i-1][j-1] + quality[i]). Then dp[i][j] = ratio[i] × sumQ[i][j]. But we can optimize space. Time O(nk), space O(nk).",
            "connectsTo": null,
            "timeComplexity": null,
            "spaceComplexity": null,
            "commonMistakes": [
              "not sorting",
              "incorrect DP transition",
              "not handling large values. Connection: This integrates all lower-level concepts into final solution"
            ],
            "codePattern": null,
            "algorithm": null,
            "summary": null
          },
          "examples": [
            {
              "input": "quality = [10,20,5], wage = [70,50,30], k = 2",
              "output": "105.0",
              "trace": "Step 1: Compute ratios: worker0: 70/10=7.0, worker1: 50/20=2.5, worker2: 30/5=6.0. Step 2: Sort by ratio: indices [1(2.5),2(6.0),0(7.0)] with qualities [20,5,10]. Step 3: Initialize dp[0][0]=0, others inf. sumQ[0][0]=0. Step 4: i=1 (worker1, ratio=2.5, quality=20): For j=1: sumQ[1][1]=min(inf, 0+20)=20, dp[1][1]=2.5*20=50.0. Step 5: i=2 (worker2, ratio=6.0, quality=5): For j=1: sumQ[2][1]=min(20, 0+5)=5, dp[2][1]=6.0*5=30.0. For j=2: sumQ[2][2]=min(inf, 20+5)=25, dp[2][2]=6.0*25=150.0. Step 6: i=3 (worker0, ratio=7.0, quality=10): For j=1: sumQ[3][1]=min(5, 0+10)=5, dp[3][1]=7.0*5=35.0. For j=2: sumQ[3][2]=min(25, 20+10)=25, dp[3][2]=7.0*25=175.0. Step 7: Find min dp[i][2] for i>=2: dp[2][2]=150.0, dp[3][2]=175.0, min=150.0? Wait, but answer should be 105.0. Error: Our DP formula is wrong. Correct approach: After sorting, for each worker i as maximum ratio, we need minimum sum of qualities of j-1 workers from previous with smallest qualities. So we use DP to track minimum sum of qualities for each count j, but cost = ratio[i] × (sum of qualities of j workers including i). So for each i, we consider hiring i as maximum ratio, and pick j-1 workers from first i-1 with smallest qualities. So we can sort qualities ascending for previous workers. Actually, simpler: Sort workers by ratio. Let dp[i][j] = minimum total cost for j workers from first i where worker i is hired (so max ratio = ratio[i]). Then dp[i][j] = ratio[i] × (quality[i] + min sum of qualities of j-1 workers from first i-1). We can precompute prefix min sums. But standard DP: Let f[i][j] = minimum sum of qualities for j workers from first i. Then f[i][j] = min(f[i-1][j], f[i-1][j-1] + quality[i]). Then answer = min over i (ratio[i] × f[i][k]). Let's recompute: Step 1: ratios and qualities as above. Step 2: Sort by ratio: workers: [(2.5,20), (6.0,5), (7.0,10)]. Step 3: Initialize f[0][0]=0, others inf. Step 4: i=1: f[1][0]=0, f[1][1]=20. Step 5: i=2: f[2][0]=0, f[2][1]=min(20,5)=5, f[2][2]=20+5=25. Step 6: i=3: f[3][0]=0, f[3][1]=min(5,10)=5, f[3][2]=min(25, 20+10)=25. Step 7: For k=2, min cost: i=2: 6.0*25=150.0, i=3: 7.0*25=175.0, min=150.0. Still not 105.0. Let's brute force: Hire workers 1 and 2: cost = max(2.5,6.0)* (20+5)=6.0*25=150.0. Hire workers 1 and 0: cost = max(2.5,7.0)* (20+10)=7.0*30=210.0. Hire workers 2 and 0: cost = max(6.0,7.0)* (5+10)=7.0*15=105.0. So answer 105.0. Our DP missed combination (2,0) because after sorting, worker0 is last, and when i=3, f[3][2] considers workers (1,0) or (2,0)? f[3][2]=min(f[2][2], f[2][1]+quality[3]) = min(25, 5+10)=15. Yes! I made error: f[2][1] is 5 (worker2), so f[3][2]=15. Then cost for i=3: 7.0*15=105.0. So correct trace: Step 1-3 as above. Step 4: i=1: f[1][1]=20. Step 5: i=2: f[2][1]=5, f[2][2]=25. Step 6: i=3: f[3][1]=5, f[3][2]=min(25, 5+10)=15. Step 7: min cost: i=2: 6.0*25=150.0, i=3: 7.0*15=105.0, min=105.0."
            },
            {
              "input": "quality = [3,1,10,10,1], wage = [4,8,2,2,8], k = 3",
              "output": "30.666666666666668",
              "trace": "Step 1: Compute ratios: w0:4/3≈1.333, w1:8/1=8.0, w2:2/10=0.2, w3:2/10=0.2, w4:8/1=8.0. Step 2: Sort by ratio: indices [2(0.2),3(0.2),0(1.333),1(8.0),4(8.0)] with qualities [10,10,3,1,1]. Step 3: Initialize f[0][0]=0. Step 4: i=1 (ratio=0.2, q=10): f[1][1]=10. Step 5: i=2 (ratio=0.2, q=10): f[2][1]=min(10,10)=10, f[2][2]=10+10=20. Step 6: i=3 (ratio=1.333, q=3): f[3][1]=min(10,3)=3, f[3][2]=min(20, 10+3)=13, f[3][3]=min(inf, 20+3)=23. Step 7: i=4 (ratio=8.0, q=1): f[4][1]=min(3,1)=1, f[4][2]=min(13, 10+1)=11, f[4][3]=min(23, 20+1)=21. Step 8: i=5 (ratio=8.0, q=1): f[5][1]=min(1,1)=1, f[5][2]=min(11, 10+1)=11, f[5][3]=min(21, 20+1)=21. Step 9: For k=3, min cost: i=3: 1.333*23≈30.666, i=4: 8.0*21=168.0, i=5: 8.0*21=168.0, min≈30.6667."
            }
          ],
          "testCases": [
            {
              "input": "quality = [10,20,5], wage = [70,50,30], k = 2",
              "expected": "105.0"
            },
            {
              "input": "quality = [3,1,10,10,1], wage = [4,8,2,2,8], k = 3",
              "expected": "30.666666666666668"
            },
            {
              "input": "quality = [1], wage = [1], k = 1",
              "expected": "1.0"
            },
            {
              "input": "quality = [1,2,3], wage = [1,2,3], k = 3",
              "expected": "6.0"
            },
            {
              "input": "quality = [10,20,30], wage = [10,20,30], k = 2",
              "expected": "30.0"
            },
            {
              "input": "quality = [5,5,5], wage = [10,20,30], k = 2",
              "expected": "40.0"
            },
            {
              "input": "quality = [100,50,25], wage = [10,20,40], k = 2",
              "expected": "53.333333333333336"
            },
            {
              "input": "quality = [2,3,4,5], wage = [1,2,3,4], k = 2",
              "expected": "4.0"
            },
            {
              "input": "quality = [1,1,1,1], wage = [1,1,1,1], k = 4",
              "expected": "4.0"
            },
            {
              "input": "quality = [100,200,300], wage = [50,100,150], k = 1",
              "expected": "50.0"
            }
          ]
        },
        {
          "level": 1,
          "title": "Key Sub-routine — DP Table for Minimum Sum of Qualities",
          "desc": "Compute minimum sum of qualities for selecting j workers from first i workers using DP.",
          "explanation": {
            "prose": "This sub-routine builds a DP table f[i][j] where f[i][j] = minimum sum of qualities when selecting exactly j workers from the first i workers (sorted by wage/quality ratio). The intuition is to incrementally decide whether to include worker i or not. Base case: f[0][0] = 0 (no workers, sum 0), and f[0][j] = infinity for j>0 (impossible). Transition: For worker i (1-indexed), we have two options: 1) Skip worker i: then sum is f[i-1][j]. 2) Include worker i: then sum is f[i-1][j-1] + quality[i]. We take the minimum: f[i][j] = min(f[i-1][j], f[i-1][j-1] + quality[i]). This works because we assume workers are sorted, but the DP itself doesn't depend on sorting; sorting is needed for the main problem to ensure ratio constraints. Time complexity O(nk) as we fill n×k table. Space O(nk) but can be optimized to O(k) by reusing rows.",
            "connectsTo": {
              "level": "L0",
              "reason": "This DP table provides the minimum sum of qualities, which when multiplied by the appropriate ratio gives the cost in the full solution"
            },
            "timeComplexity": null,
            "spaceComplexity": null,
            "commonMistakes": [
              "incorrect initialization",
              "off-by-one indices",
              "not handling infinity for impossible states"
            ],
            "codePattern": null,
            "algorithm": null,
            "summary": null
          },
          "examples": [
            {
              "input": "qualities = [20,5,10], k = 2",
              "output": "f[3][2] = 15",
              "trace": "Step 1: Initialize f[0][0]=0, f[0][1]=inf, f[0][2]=inf. Step 2: i=1, quality=20: f[1][0]=0, f[1][1]=min(inf, 0+20)=20, f[1][2]=min(inf, inf+20)=inf. Step 3: i=2, quality=5: f[2][0]=0, f[2][1]=min(20, 0+5)=5, f[2][2]=min(inf, 20+5)=25. Step 4: i=3, quality=10: f[3][0]=0, f[3][1]=min(5, 0+10)=5, f[3][2]=min(25, 5+10)=15. So f[3][2]=15."
            },
            {
              "input": "qualities = [10,10,3,1,1], k = 3",
              "output": "f[5][3] = 21",
              "trace": "Step 1: Initialize f[0][0]=0, f[0][1]=inf, f[0][2]=inf, f[0][3]=inf. Step 2: i=1, q=10: f[1][1]=10. Step 3: i=2, q=10: f[2][1]=min(10,10)=10, f[2][2]=20. Step 4: i=3, q=3: f[3][1]=min(10,3)=3, f[3][2]=min(20,10+3)=13, f[3][3]=23. Step 5: i=4, q=1: f[4][1]=min(3,1)=1, f[4][2]=min(13,10+1)=11, f[4][3]=min(23,20+1)=21. Step 6: i=5, q=1: f[5][1]=min(1,1)=1, f[5][2]=min(11,10+1)=11, f[5][3]=min(21,20+1)=21. So f[5][3]=21."
            }
          ],
          "testCases": [
            {
              "input": "qualities = [20,5,10], k = 2",
              "expected": "15"
            },
            {
              "input": "qualities = [10,10,3,1,1], k = 3",
              "expected": "21"
            },
            {
              "input": "qualities = [1,2,3], k = 2",
              "expected": "3"
            },
            {
              "input": "qualities = [5,5,5], k = 3",
              "expected": "15"
            },
            {
              "input": "qualities = [100,50,25], k = 2",
              "expected": "75"
            },
            {
              "input": "qualities = [2,3,4,5], k = 2",
              "expected": "5"
            },
            {
              "input": "qualities = [1,1,1,1], k = 4",
              "expected": "4"
            },
            {
              "input": "qualities = [10], k = 1",
              "expected": "10"
            },
            {
              "input": "qualities = [10,20], k = 2",
              "expected": "30"
            },
            {
              "input": "qualities = [5,10,15], k = 1",
              "expected": "5"
            }
          ]
        },
        {
          "level": 2,
          "title": "Core Logic — Sorting by Wage-to-Quality Ratio",
          "desc": "Sort workers based on wage/quality ratio to enable efficient cost calculation.",
          "explanation": {
            "prose": "The core insight is that to minimize cost for hiring k workers, we need to ensure that each worker is paid at least their expected wage, and wages are proportional to quality. If we hire a set of workers, the cost is max_ratio × total_quality, where max_ratio is the maximum wage/quality ratio among hired workers. By sorting workers in ascending order of ratio, when we consider worker i as the last hired (thus having the maximum ratio in the set), all other hired workers must have ratio ≤ ratio[i], which is automatically satisfied if we pick them from indices < i. This allows us to decouple the problem: for each worker i, we need to pick k-1 workers from the first i-1 workers with minimum total quality. Sorting transforms the constraint into a selection problem. Intuition: If we fix the maximum ratio, we want to minimize total quality, and sorting ensures we only consider workers with lower or equal ratios. Step-by-step: 1) Compute ratio[i] = wage[i] / quality[i] for each worker. 2) Sort workers by ratio ascending, keeping track of qualities. 3) Now, for each i, if worker i is included, the cost is ratio[i] × (quality[i] + sum of qualities of k-1 workers from first i-1). This reduces to finding minimum sum of qualities for each count. Time O(n log n) for sorting. Space O(n).",
            "connectsTo": {
              "level": "L1",
              "reason": "Sorting enables the DP to work correctly by ensuring the ratio constraint is maintained"
            },
            "timeComplexity": null,
            "spaceComplexity": null,
            "commonMistakes": [
              "not using floating-point for ratios",
              "incorrect sorting order",
              "not preserving quality with ratio"
            ],
            "codePattern": null,
            "algorithm": null,
            "summary": null
          },
          "examples": [
            {
              "input": "quality = [10,20,5], wage = [70,50,30]",
              "output": "sorted indices: [1,2,0] with ratios [2.5,6.0,7.0] and qualities [20,5,10]",
              "trace": "Step 1: Compute ratios: worker0: 70/10=7.0, worker1: 50/20=2.5, worker2: 30/5=6.0. Step 2: Create list of (ratio, quality, index): [(7.0,10,0), (2.5,20,1), (6.0,5,2)]. Step 3: Sort by ratio: [(2.5,20,1), (6.0,5,2), (7.0,10,0)]. Step 4: Extract sorted qualities: [20,5,10] and ratios: [2.5,6.0,7.0]."
            },
            {
              "input": "quality = [3,1,10,10,1], wage = [4,8,2,2,8]",
              "output": "sorted indices: [2,3,0,1,4] with ratios [0.2,0.2,1.333,8.0,8.0] and qualities [10,10,3,1,1]",
              "trace": "Step 1: Compute ratios: w0:4/3≈1.333, w1:8/1=8.0, w2:2/10=0.2, w3:2/10=0.2, w4:8/1=8.0. Step 2: List: [(1.333,3,0), (8.0,1,1), (0.2,10,2), (0.2,10,3), (8.0,1,4)]. Step 3: Sort by ratio: [(0.2,10,2), (0.2,10,3), (1.333,3,0), (8.0,1,1), (8.0,1,4)]. Step 4: Sorted qualities: [10,10,3,1,1], ratios: [0.2,0.2,1.333,8.0,8.0]."
            }
          ],
          "testCases": [
            {
              "input": "quality = [10,20,5], wage = [70,50,30]",
              "expected": "sorted qualities: [20,5,10], ratios: [2.5,6.0,7.0]"
            },
            {
              "input": "quality = [3,1,10,10,1], wage = [4,8,2,2,8]",
              "expected": "sorted qualities: [10,10,3,1,1], ratios: [0.2,0.2,1.333,8.0,8.0]"
            },
            {
              "input": "quality = [1], wage = [1]",
              "expected": "sorted qualities: [1], ratios: [1.0]"
            },
            {
              "input": "quality = [1,2,3], wage = [1,2,3]",
              "expected": "sorted qualities: [1,2,3], ratios: [1.0,1.0,1.0]"
            },
            {
              "input": "quality = [10,20,30], wage = [10,20,30]",
              "expected": "sorted qualities: [10,20,30], ratios: [1.0,1.0,1.0]"
            },
            {
              "input": "quality = [5,5,5], wage = [10,20,30]",
              "expected": "sorted qualities: [5,5,5], ratios: [2.0,4.0,6.0]"
            },
            {
              "input": "quality = [100,50,25], wage = [10,20,40]",
              "expected": "sorted qualities: [100,25,50], ratios: [0.1,1.6,0.4]"
            },
            {
              "input": "quality = [2,3,4,5], wage = [1,2,3,4]",
              "expected": "sorted qualities: [2,3,4,5], ratios: [0.5,0.6667,0.75,0.8]"
            },
            {
              "input": "quality = [1,1,1,1], wage = [1,1,1,1]",
              "expected": "sorted qualities: [1,1,1,1], ratios: [1.0,1.0,1.0,1.0]"
            },
            {
              "input": "quality = [100,200,300], wage = [50,100,150]",
              "expected": "sorted qualities: [100,200,300], ratios: [0.5,0.5,0.5]"
            }
          ]
        },
        {
          "level": 3,
          "title": "Building Block — Selecting k-1 Minimum Elements from a List",
          "desc": "Find the smallest sum of k-1 elements from a list of numbers.",
          "explanation": {
            "prose": "This intermediate concept involves selecting exactly k-1 elements from a list to minimize their total sum. This is a classic selection problem that can be solved by sorting the list in ascending order and taking the first k-1 elements. Intuition: To minimize the sum, we pick the smallest elements available. Step-by-step: 1) Given a list of numbers (e.g., qualities), sort it in ascending order. 2) Take the first k-1 elements (if list length ≥ k-1). 3) Sum these elements to get the minimum sum. Time complexity O(n log n) for sorting, or O(n) using quickselect if only sum is needed. Space O(1) if sorting in-place.",
            "connectsTo": {
              "level": "L2",
              "reason": "In the main problem, after sorting by ratio, for each worker i, we need the minimum sum of qualities of k-1 workers from the first i-1 workers, which is a prefix selection problem solved by DP in L1, but this building block is the naive approach for a fixed list"
            },
            "timeComplexity": null,
            "spaceComplexity": null,
            "commonMistakes": [
              "not handling cases where list length < k-1 (should return infinity or handle in caller)",
              "off-by-one in index"
            ],
            "codePattern": null,
            "algorithm": null,
            "summary": null
          },
          "examples": [
            {
              "input": "list = [20,5,10], k = 2 (so k-1=1)",
              "output": "min sum = 5",
              "trace": "Step 1: List = [20,5,10]. Step 2: Sort ascending: [5,10,20]. Step 3: Take first 1 element: 5. Step 4: Sum = 5."
            },
            {
              "input": "list = [10,10,3,1,1], k = 3 (so k-1=2)",
              "output": "min sum = 2",
              "trace": "Step 1: List = [10,10,3,1,1]. Step 2: Sort ascending: [1,1,3,10,10]. Step 3: Take first 2 elements: 1 and 1. Step 4: Sum = 2."
            }
          ],
          "testCases": [
            {
              "input": "list = [20,5,10], k = 2",
              "expected": "5"
            },
            {
              "input": "list = [10,10,3,1,1], k = 3",
              "expected": "2"
            },
            {
              "input": "list = [1,2,3], k = 2",
              "expected": "1"
            },
            {
              "input": "list = [5,5,5], k = 3",
              "expected": "10"
            },
            {
              "input": "list = [100,50,25], k = 2",
              "expected": "25"
            },
            {
              "input": "list = [2,3,4,5], k = 2",
              "expected": "2"
            },
            {
              "input": "list = [1,1,1,1], k = 4",
              "expected": "3"
            },
            {
              "input": "list = [10], k = 1",
              "expected": "0"
            },
            {
              "input": "list = [10,20], k = 2",
              "expected": "10"
            },
            {
              "input": "list = [5,10,15], k = 1",
              "expected": "0"
            }
          ]
        },
        {
          "level": 4,
          "title": "Basic Operation — Computing Wage-to-Quality Ratio",
          "desc": "Calculate the ratio of wage to quality for a worker.",
          "explanation": {
            "prose": "This fundamental operation computes the ratio r = wage / quality for a single worker. The ratio represents the cost per unit of quality for that worker. Intuition: If a worker has wage w and quality q, then to pay them fairly, the wage must be at least w, and if we pay them at a rate r per quality, then wage = r × q. So r = w/q is the minimum ratio needed to satisfy their wage constraint. Step-by-step: 1) Take wage and quality as inputs. 2) If quality is 0, handle as error (but in problem, quality > 0). 3) Compute ratio = wage / quality using floating-point division to handle non-integer results. 4) Return ratio. Time O(1), space O(1).",
            "connectsTo": {
              "level": "L3",
              "reason": "This ratio is used to sort workers, which is essential for the selection process"
            },
            "timeComplexity": null,
            "spaceComplexity": null,
            "commonMistakes": [
              "using integer division",
              "not handling division by zero",
              "precision issues with floats"
            ],
            "codePattern": null,
            "algorithm": null,
            "summary": null
          },
          "examples": [
            {
              "input": "wage = 70, quality = 10",
              "output": "7.0",
              "trace": "Step 1: wage = 70, quality = 10. Step 2: ratio = 70 / 10 = 7.0."
            },
            {
              "input": "wage = 50, quality = 20",
              "output": "2.5",
              "trace": "Step 1: wage = 50, quality = 20. Step 2: ratio = 50 / 20 = 2.5."
            }
          ],
          "testCases": [
            {
              "input": "wage = 70, quality = 10",
              "expected": "7.0"
            },
            {
              "input": "wage = 50, quality = 20",
              "expected": "2.5"
            },
            {
              "input": "wage = 30, quality = 5",
              "expected": "6.0"
            },
            {
              "input": "wage = 4, quality = 3",
              "expected": "1.3333333333333333"
            },
            {
              "input": "wage = 8, quality = 1",
              "expected": "8.0"
            },
            {
              "input": "wage = 2, quality = 10",
              "expected": "0.2"
            },
            {
              "input": "wage = 1, quality = 1",
              "expected": "1.0"
            },
            {
              "input": "wage = 10, quality = 10",
              "expected": "1.0"
            },
            {
              "input": "wage = 20, quality = 5",
              "expected": "4.0"
            },
            {
              "input": "wage = 100, quality = 200",
              "expected": "0.5"
            }
          ]
        },
        {
          "level": 5,
          "title": "Concept Foundation — Understanding Ratio and Proportion",
          "desc": "Basic concept of ratio and proportional relationships.",
          "explanation": {
            "prose": "This foundational concept introduces the idea of a ratio as a comparison of two quantities, and proportion as an equation stating that two ratios are equal. In the context of the problem, each worker has a wage (money) and quality (work output). The ratio wage/quality represents how much money is paid per unit of quality. If we pay all workers at the same rate r (dollars per quality point), then each worker i receives wage_i = r × quality_i. To satisfy that worker i is paid at least their expected wage, we need r ≥ wage_i / quality_i. Thus, if we hire a group of workers, we must pay at rate r ≥ max(wage_i/quality_i) for all i in the group. The total cost is r × sum(quality_i). Intuition: Higher ratio means more expensive per quality, so to minimize cost, we want to keep r low while meeting all wage constraints. Step-by-step: 1) Ratio a:b means a/b. 2) Proportional: if a/b = c/d, then a and c are proportional to b and d. 3) In problem, r is the proportionality constant. Example: Worker A: wage=$70, quality=10, ratio=7. Worker B: wage=$50, quality=20, ratio=2.5. If we pay at rate r=7, then A gets 7×10=$70 (ok), B gets 7×20=$140 (exceeds $50, so ok). Total cost depends on sum of qualities.",
            "connectsTo": {
              "level": "L4",
              "reason": "This concept underpins why we compute wage/quality ratio"
            },
            "timeComplexity": null,
            "spaceComplexity": null,
            "commonMistakes": [
              "confusing ratio with difference",
              "not understanding that r must be at least the maximum ratio"
            ],
            "codePattern": null,
            "algorithm": null,
            "summary": null
          },
          "examples": [
            {
              "input": "Worker A: wage=70, quality=10; Worker B: wage=50, quality=20. What rate r ensures both are paid at least their wage?",
              "output": "r must be at least 7.0",
              "trace": "Step 1: Compute ratios: A: 70/10=7.0, B: 50/20=2.5. Step 2: To pay A enough, r must be ≥7.0. Step 3: To pay B enough, r must be ≥2.5. Step 4: The maximum is 7.0, so r ≥7.0 ensures both are paid at least their wage. If r=7.0, A gets 7.0×10=70 (exact), B gets 7.0×20=140 (more than 50)."
            },
            {
              "input": "Worker X: wage=10, quality=5; Worker Y: wage=20, quality=10. What is the minimum r?",
              "output": "r must be at least 2.0",
              "trace": "Step 1: Ratios: X: 10/5=2.0, Y: 20/10=2.0. Step 2: Both ratios are 2.0, so r must be ≥2.0. If r=2.0, X gets 2.0×5=10 (exact), Y gets 2.0×10=20 (exact)."
            }
          ],
          "testCases": [
            {
              "input": "wage=70, quality=10",
              "expected": "ratio=7.0"
            },
            {
              "input": "wage=50, quality=20",
              "expected": "ratio=2.5"
            },
            {
              "input": "wage=30, quality=5",
              "expected": "ratio=6.0"
            },
            {
              "input": "wage=4, quality=3",
              "expected": "ratio≈1.333"
            },
            {
              "input": "wage=8, quality=1",
              "expected": "ratio=8.0"
            },
            {
              "input": "wage=2, quality=10",
              "expected": "ratio=0.2"
            },
            {
              "input": "wage=1, quality=1",
              "expected": "ratio=1.0"
            },
            {
              "input": "wage=10, quality=10",
              "expected": "ratio=1.0"
            },
            {
              "input": "wage=20, quality=5",
              "expected": "ratio=4.0"
            },
            {
              "input": "wage=100, quality=200",
              "expected": "ratio=0.5"
            }
          ]
        }
      ]
    }
  ]
}